vlite/__init__.py
vlite/ctx.py
vlite/index.py
vlite/main.py
vlite/model.py
vlite/omom.py
vlite/server.py
vlite/utils.py
vlite-0.2.4.dist-info/LICENSE
vlite-0.2.4.dist-info/METADATA
vlite-0.2.4.dist-info/WHEEL
vlite-0.2.4.dist-info/top_level.txt
vlite-0.2.4.dist-info/RECORD
